{
  "m_GameObject": {
    "m_FileID": 0,
    "m_PathID": 0
  },
  "m_Enabled": 1,
  "m_Script": {
    "m_FileID": 0,
    "m_PathID": -6831197485353024473
  },
  "m_Name": "portraits#75",
  "_sprites": [
    {
      "name": "char_449_glider_nian#10",
      "guid": "86f6b007f1e4d6045967805803613ad2",
      "atlas": 0,
      "rect": {
        "x": 0,
        "y": 0,
        "w": 180,
        "h": 360
      },
      "rotate": 0
    },
    {
      "name": "char_4116_blkkgt_1",
      "guid": "0d4e70849aea0884eb842203e8084924",
      "atlas": 0,
      "rect": {
        "x": 182,
        "y": 0,
        "w": 180,
        "h": 360
      },
      "rotate": 0
    },
    {
      "name": "char_4114_harold_2",
      "guid": "7574962484283604faed0928ccd86cea",
      "atlas": 0,
      "rect": {
        "x": 0,
        "y": 362,
        "w": 180,
        "h": 360
      },
      "rotate": 0
    },
    {
      "name": "char_4114_harold_1",
      "guid": "0d5542b2cd5b0894b8e84f54bcf85524",
      "atlas": 0,
      "rect": {
        "x": 182,
        "y": 362,
        "w": 180,
        "h": 360
      },
      "rotate": 0
    },
    {
      "name": "char_4107_vrdant_2",
      "guid": "0e39a9587003bd444b8d2041eb5e1e46",
      "atlas": 0,
      "rect": {
        "x": 364,
        "y": 0,
        "w": 180,
        "h": 360
      },
      "rotate": 0
    },
    {
      "name": "char_4107_vrdant_1",
      "guid": "c21c7f89ff2748243a21f3907aea4ad1",
      "atlas": 0,
      "rect": {
        "x": 364,
        "y": 362,
        "w": 180,
        "h": 360
      },
      "rotate": 0
    },
    {
      "name": "char_4081_warmy_2",
      "guid": "8b56eb21a19a93c44a1799632f70d54d",
      "atlas": 0,
      "rect": {
        "x": 546,
        "y": 0,
        "w": 180,
        "h": 360
      },
      "rotate": 0
    },
    {
      "name": "char_4080_lin_nian#10",
      "guid": "5ee10dd9c87a400439e7c1a1b2cb65f3",
      "atlas": 0,
      "rect": {
        "x": 546,
        "y": 362,
        "w": 180,
        "h": 360
      },
      "rotate": 0
    },
    {
      "name": "char_4066_highmo_nian#10",
      "guid": "7db14404f76d35e4d83a0d99a175f425",
      "atlas": 0,
      "rect": {
        "x": 728,
        "y": 0,
        "w": 180,
        "h": 360
      },
      "rotate": 0
    },
    {
      "name": "char_2025_shu_2",
      "guid": "61539b360a855bc41adb0dbeaefe64a7",
      "atlas": 0,
      "rect": {
        "x": 728,
        "y": 362,
        "w": 180,
        "h": 360
      },
      "rotate": 0
    },
    {
      "name": "char_2025_shu_1",
      "guid": "c839537c9be6abd41b20a702708786b4",
      "atlas": 0,
      "rect": {
        "x": 0,
        "y": 724,
        "w": 360,
        "h": 180
      },
      "rotate": 1
    }
  ],
  "_atlas": {
    "index": 0,
    "texture": {
      "m_FileID": 0,
      "m_PathID": -7897156595478689742
    },
    "alpha": {
      "m_FileID": 0,
      "m_PathID": -1152285500921312982
    },
    "size": 1024
  },
  "_index": 75,
  "_sign": {
    "m_sprites": [
      {
        "name": "char_449_glider_nian#10",
        "guid": "86f6b007f1e4d6045967805803613ad2",
        "md5": "af54e1bf7b00450e1fb1cd456faa38f1"
      },
      {
        "name": "char_4116_blkkgt_1",
        "guid": "0d4e70849aea0884eb842203e8084924",
        "md5": "169d7d3ca3435b659b75fcadcdbeb2d6"
      },
      {
        "name": "char_4114_harold_2",
        "guid": "7574962484283604faed0928ccd86cea",
        "md5": "cb71647b4b8f8e7b459e3bf1835b91d8"
      },
      {
        "name": "char_4114_harold_1",
        "guid": "0d5542b2cd5b0894b8e84f54bcf85524",
        "md5": "693b757b98a43bccb32171423723086b"
      },
      {
        "name": "char_4107_vrdant_2",
        "guid": "0e39a9587003bd444b8d2041eb5e1e46",
        "md5": "fdd5d07b5ef8992d07f4c9ffaf6efe76"
      },
      {
        "name": "char_4107_vrdant_1",
        "guid": "c21c7f89ff2748243a21f3907aea4ad1",
        "md5": "7de71f837e482ad6d7e5002ddc743182"
      },
      {
        "name": "char_4081_warmy_2",
        "guid": "8b56eb21a19a93c44a1799632f70d54d",
        "md5": "2e6afe95f6e96210d8ebe784a924fd9d"
      },
      {
        "name": "char_4080_lin_nian#10",
        "guid": "5ee10dd9c87a400439e7c1a1b2cb65f3",
        "md5": "ce9af389c72520950e55e89697ed8370"
      },
      {
        "name": "char_4066_highmo_nian#10",
        "guid": "7db14404f76d35e4d83a0d99a175f425",
        "md5": "015988cbd04d943e3ea07eca79287251"
      },
      {
        "name": "char_2025_shu_2",
        "guid": "61539b360a855bc41adb0dbeaefe64a7",
        "md5": "119b59da30660a9174eabb9e4e143433"
      },
      {
        "name": "char_2025_shu_1",
        "guid": "c839537c9be6abd41b20a702708786b4",
        "md5": "4035ea605af1e7c67c1e782313a06262"
      }
    ],
    "m_atlases": [
      {
        "name": "portraits#75",
        "guid": "a496beea5455d424f894405f5884033c",
        "md5": "1fc0a17da229cd6d8e019e485392bf97"
      }
    ],
    "m_alphas": [
      {
        "name": "portraits#75a",
        "guid": "3b52934fe07f4c74389caed875dfb8ea",
        "md5": "26ac2157630b9ed5eb2fe14d53f6dc9d"
      }
    ]
  }
}